AUTHORS.rst
CHANGELOG.rst
LICENSE
MANIFEST.in
README.rst
setup.py
ambient/__init__.py
python_ambient.egg-info/PKG-INFO
python_ambient.egg-info/SOURCES.txt
python_ambient.egg-info/dependency_links.txt
python_ambient.egg-info/not-zip-safe
python_ambient.egg-info/top_level.txt