Metadata-Version: 1.1
Name: python-ambient
Version: 0.0.7
Summary: Python Ambient Mobile integration library.
Home-page: http://github.com/praekelt/python-ambient
Author: Praekelt Foundation
Author-email: dev@praekelt.com
License: BSD
Platform: UNKNOWN
Classifier: Programming Language :: Python
Classifier: License :: OSI Approved :: BSD License
Classifier: Development Status :: 4 - Beta
Classifier: Operating System :: OS Independent
Classifier: Intended Audience :: Developers
